odoo/addons/partner_deduplicate_acl/README.rst
odoo/addons/partner_deduplicate_acl/__init__.py
odoo/addons/partner_deduplicate_acl/__manifest__.py
odoo/addons/partner_deduplicate_acl/i18n/de.po
odoo/addons/partner_deduplicate_acl/i18n/es.po
odoo/addons/partner_deduplicate_acl/i18n/fr.po
odoo/addons/partner_deduplicate_acl/i18n/hr.po
odoo/addons/partner_deduplicate_acl/i18n/it.po
odoo/addons/partner_deduplicate_acl/i18n/nl_NL.po
odoo/addons/partner_deduplicate_acl/i18n/partner_deduplicate_acl.pot
odoo/addons/partner_deduplicate_acl/i18n/pt_BR.po
odoo/addons/partner_deduplicate_acl/i18n/sk.po
odoo/addons/partner_deduplicate_acl/i18n/sl.po
odoo/addons/partner_deduplicate_acl/i18n/tr.po
odoo/addons/partner_deduplicate_acl/i18n/zh_CN.po
odoo/addons/partner_deduplicate_acl/images/perms.png
odoo/addons/partner_deduplicate_acl/readme/CONFIGURE.md
odoo/addons/partner_deduplicate_acl/readme/CONTRIBUTORS.md
odoo/addons/partner_deduplicate_acl/readme/DESCRIPTION.md
odoo/addons/partner_deduplicate_acl/readme/USAGE.md
odoo/addons/partner_deduplicate_acl/security/ir.model.access.csv
odoo/addons/partner_deduplicate_acl/security/partner_deduplicate_acl_security.xml
odoo/addons/partner_deduplicate_acl/static/description/icon.png
odoo/addons/partner_deduplicate_acl/static/description/icon.svg
odoo/addons/partner_deduplicate_acl/static/description/index.html
odoo/addons/partner_deduplicate_acl/tests/__init__.py
odoo/addons/partner_deduplicate_acl/tests/test_partner_deduplicate_acl.py
odoo/addons/partner_deduplicate_acl/views/base_partner_merge_view.xml
odoo/addons/partner_deduplicate_acl/wizards/__init__.py
odoo/addons/partner_deduplicate_acl/wizards/partner_merge.py
odoo/addons/partner_deduplicate_acl/wizards/partner_merge_view.xml
odoo_addon_partner_deduplicate_acl-18.0.1.0.0.2.dist-info/METADATA
odoo_addon_partner_deduplicate_acl-18.0.1.0.0.2.dist-info/WHEEL
odoo_addon_partner_deduplicate_acl-18.0.1.0.0.2.dist-info/top_level.txt
odoo_addon_partner_deduplicate_acl-18.0.1.0.0.2.dist-info/RECORD
